tiny_dungeon/__init__.py
tiny_dungeon/char.py
tiny_dungeon/data.py
tiny_dungeon-0.9.0.dist-info/METADATA
tiny_dungeon-0.9.0.dist-info/WHEEL
tiny_dungeon-0.9.0.dist-info/top_level.txt
tiny_dungeon-0.9.0.dist-info/RECORD
