Metadata-Version: 2.1
Name: tiny_dungeon
Version: 0.9.0
Summary: Character Generator for the Tiny Dungeon RPG (1st Edition)
Author: Jeremy Deram
Project-URL: homepage, https://github.com/jderam/tiny-dungeon-chargen
Keywords: Dungeons,Dragons,Tiny Dungeon,RPG
Classifier: Programming Language :: Python :: 3
Classifier: Programming Language :: Python :: 3 :: Only
Classifier: Programming Language :: Python :: 3.9
Classifier: Programming Language :: Python :: 3.10
Classifier: Programming Language :: Python :: 3.11
Classifier: License :: OSI Approved :: MIT License
Classifier: Operating System :: OS Independent
Requires-Python: >=3.8
Provides-Extra: dev
Requires-Dist: build ; extra == 'dev'
Requires-Dist: pre-commit ; extra == 'dev'
Requires-Dist: pytest ; extra == 'dev'
Requires-Dist: pytest-cov ; extra == 'dev'
Requires-Dist: ruff ; extra == 'dev'
Requires-Dist: twine ; extra == 'dev'
